[
    {
        "frameRange": [
            0,
            0
        ],
        "activity": "no_presence"
    },
    {
        "frameRange": [
            1,
            8
        ],
        "activity": "walking"
    },
    {
        "frameRange": [
            9,
            11
        ],
        "activity": "no_activity"
    },
    {
        "frameRange": [
            12,
            23
        ],
        "activity": "walking"
    },
    {
        "frameRange": [
            24,
            25
        ],
        "activity": "sitting"
    },
    {
        "frameRange": [
            26,
            26
        ],
        "activity": "standing"
    },
    {
        "frameRange": [
            27,
            32
        ],
        "activity": "sitting"
    },
    {
        "frameRange": [
            33,
            36
        ],
        "activity": "no_activity"
    },
    {
        "frameRange": [
            37,
            38
        ],
        "activity": "walking"
    },
    {
        "frameRange": [
            39,
            84
        ],
        "activity": "no_activity"
    },
    {
        "frameRange": [
            85,
            89
        ],
        "activity": "standing"
    },
    {
        "frameRange": [
            90,
            101
        ],
        "activity": "no_activity"
    }
]