{"videoId":351356885,"datasetId":1031394,"videoName":"video_20250227_152742_994.mp4","createdAt":"2025-03-17T04:56:40.816Z","updatedAt":"2025-03-17T08:49:30.876Z","link":null,"description":"","tags":[{"name":"no_activity","id":166700401,"tagId":32823650,"frameRange":[0,36],"labelerLogin":"yongjoon1212@gmail.com","createdAt":"2025-03-17T08:49:25.581Z","updatedAt":"2025-03-17T08:49:30.102Z","isFinished":true,"nonFinalValue":false},{"name":"walking","id":166700415,"tagId":32823653,"frameRange":[36,101],"labelerLogin":"yongjoon1212@gmail.com","createdAt":"2025-03-17T08:49:30.869Z","updatedAt":"2025-03-17T08:49:35.673Z","isFinished":true,"nonFinalValue":false}],"objects":[],"size":{"height":1080,"width":1920},"framesCount":102,"frames":[]}