[
    {
        "frameRange": [
            0,
            63
        ],
        "activity": "walking"
    },
    {
        "frameRange": [
            64,
            65
        ],
        "activity": "no_activity"
    },
    {
        "frameRange": [
            66,
            66
        ],
        "activity": "walking"
    },
    {
        "frameRange": [
            67,
            69
        ],
        "activity": "no_activity"
    },
    {
        "frameRange": [
            70,
            70
        ],
        "activity": "walking"
    },
    {
        "frameRange": [
            71,
            101
        ],
        "activity": "no_activity"
    }
]