[
    {
        "frameRange": [
            0,
            11
        ],
        "activity": "sitting"
    },
    {
        "frameRange": [
            11,
            46
        ],
        "activity": "no_activity"
    },
    {
        "frameRange": [
            46,
            62
        ],
        "activity": "standing"
    },
    {
        "frameRange": [
            62,
            96
        ],
        "activity": "no_activity"
    },
    {
        "frameRange": [
            96,
            101
        ],
        "activity": "sitting"
    }
]