[
    {
        "frameRange": [
            0,
            3
        ],
        "activity": "no_activity"
    },
    {
        "frameRange": [
            4,
            4
        ],
        "activity": "sitting"
    },
    {
        "frameRange": [
            5,
            5
        ],
        "activity": "no_activity"
    },
    {
        "frameRange": [
            6,
            28
        ],
        "activity": "sitting"
    },
    {
        "frameRange": [
            29,
            64
        ],
        "activity": "no_activity"
    },
    {
        "frameRange": [
            65,
            85
        ],
        "activity": "standing"
    },
    {
        "frameRange": [
            86,
            101
        ],
        "activity": "no_activity"
    }
]